{
	"mqttUrl": "mqtt://127.0.0.1"
	,"topic": "pingOtronic/ping"
	,"mongodbUri": "mongodb://myUserAdmin:88Cipolle!@10.0.2.2:27017/Customer?authMechanism=DEFAULT&authSource=admin"
	,"mqttOptions": {}
	,"pingTimeout" : 3000
	,"timeMarker": 5000
	,"ttlOut": 9999
	,"rttOut": 9999
	,"hostViewPort": 3001
	,"hostFnName": "/home/ingestor/ingestor/hostNames.txt"
	,"procesCtrlFnName": "/home/ingestor/ingestor/ingestor.run"
	,"HostListDeep": "48 hour"
	,"BadHostListDeep": "24 hour"
	,"SessionSecretKey": "<skjfhsl<zchxo89u8u32nm,a7661887"
	,"cookieSecretKey": "saf4wad67788##@sa21pp$pelzkPmnbv"
}